setup.py
jjb_reactive_choice_param/__init__.py
jjb_reactive_choice_param/reactive_choice_param.py
jjb_reactive_choice_param.egg-info/PKG-INFO
jjb_reactive_choice_param.egg-info/SOURCES.txt
jjb_reactive_choice_param.egg-info/dependency_links.txt
jjb_reactive_choice_param.egg-info/entry_points.txt
jjb_reactive_choice_param.egg-info/top_level.txt