Metadata-Version: 1.1
Name: jjb-reactive-choice-param
Version: 0.3.0
Summary: Jenkins Job Builder Reactive Choice Param
Home-page: https://github.com/ochirkov/jenkins-job-builder-active-choice-reactive-param
Author: Chyrkov Oleksandr
Author-email: ironloriin20@gmail.com
License: Apache-2.0 license
Platform: UNKNOWN
Classifier: Environment :: Console
Classifier: Intended Audience :: Developers
Classifier: Intended Audience :: Information Technology
Classifier: License :: OSI Approved :: Apache Software License
Classifier: Operating System :: OS Independent
Classifier: Programming Language :: Python
Classifier: Programming Language :: Python :: 2
Classifier: Programming Language :: Python :: 3
